<annotation>
	<folder>Mig-29</folder>
	<filename>25991_1460997969.jpg</filename>
	<path>C:\Users\NOVOAIR\Desktop\Mig-29\25991_1460997969.jpg</path>
	<source>
		<database>Unknown</database>
	</source>
	<size>
		<width>1200</width>
		<height>694</height>
		<depth>3</depth>
	</size>
	<segmented>0</segmented>
	<object>
		<name>Mig-29</name>
		<pose>Unspecified</pose>
		<truncated>0</truncated>
		<difficult>0</difficult>
		<bndbox>
			<xmin>52</xmin>
			<ymin>165</ymin>
			<xmax>1118</xmax>
			<ymax>479</ymax>
		</bndbox>
	</object>
</annotation>
