<annotation>
	<folder>chinook</folder>
	<filename>MH-47-Chinook-USS-Kearsarge-small-1170x610~1.jpg</filename>
	<path>C:\Users\NOVOAIR\Desktop\chinook\MH-47-Chinook-USS-Kearsarge-small-1170x610~1.jpg</path>
	<source>
		<database>Unknown</database>
	</source>
	<size>
		<width>1170</width>
		<height>610</height>
		<depth>3</depth>
	</size>
	<segmented>0</segmented>
	<object>
		<name>chinook</name>
		<pose>Unspecified</pose>
		<truncated>0</truncated>
		<difficult>0</difficult>
		<bndbox>
			<xmin>131</xmin>
			<ymin>179</ymin>
			<xmax>1145</xmax>
			<ymax>517</ymax>
		</bndbox>
	</object>
</annotation>
